hyperframe/__init__.py
hyperframe/hyperpattern.py
hyperframe/py.typed
hyperframe/tabulate.py
html_hyperframe-0.2.0.dist-info/LICENSE
html_hyperframe-0.2.0.dist-info/METADATA
html_hyperframe-0.2.0.dist-info/WHEEL
html_hyperframe-0.2.0.dist-info/RECORD
