Metadata-Version: 2.3
Name: html-hyperframe
Version: 0.2.0
Summary: 
Author: SamB
Author-email: 58937194+sam-lawrence@users.noreply.github.com
Requires-Python: >=3.9,<4.0
Classifier: Operating System :: OS Independent
Classifier: Programming Language :: Python :: 3
Classifier: Programming Language :: Python :: 3.9
Classifier: Programming Language :: Python :: 3.10
Classifier: Programming Language :: Python :: 3.11
Classifier: Programming Language :: Python :: 3.12
Classifier: Programming Language :: Python :: 3.13
Classifier: Programming Language :: Python :: 3 :: Only
Requires-Dist: beautifulsoup4 (>=4)
Requires-Dist: lxml (>5,<6)
Requires-Dist: pandas (>=2,<3)
Project-URL: Repository, https://github.com/sam-lawrence/HyperFrame
